pulumi_tls/__init__.py
pulumi_tls/_inputs.py
pulumi_tls/_utilities.py
pulumi_tls/cert_request.py
pulumi_tls/get_certificate.py
pulumi_tls/get_public_key.py
pulumi_tls/locally_signed_cert.py
pulumi_tls/outputs.py
pulumi_tls/private_key.py
pulumi_tls/provider.py
pulumi_tls/pulumi-plugin.json
pulumi_tls/py.typed
pulumi_tls/self_signed_cert.py
pulumi_tls/config/__init__.py
pulumi_tls/config/__init__.pyi
pulumi_tls/config/outputs.py
pulumi_tls/config/vars.py
pulumi_tls-5.3.0.dist-info/METADATA
pulumi_tls-5.3.0.dist-info/WHEEL
pulumi_tls-5.3.0.dist-info/top_level.txt
pulumi_tls-5.3.0.dist-info/RECORD
